<?xml version="1.0" encoding="UTF-8"?>
<annotation>
  <ver>v001_1</ver>
  <folder>2</folder>
  <filename>2_20200114_155214_000060.jpg</filename>
  <path>C:\Users\KATECH-01\Desktop\v3\02. 검수_도심로4차_5차_신성례v3\도심로 5차\20200114_155214\2\</path>
  <source>
    <database>KATECH_DB</database>
  </source>
  <size>
    <width>1920</width>
    <height>1080</height>
    <depth>3</depth>
  </size>
  <segmented>0</segmented>
  <index_max>26</index_max>
  <object>
    <name>RoadMark_StopLine</name>
    <pose>Unspecified</pose>
    <truncated>0</truncated>
    <difficult>0</difficult>
    <bndbox>
      <xmin>481</xmin>
      <ymin>673</ymin>
      <xmax>760</xmax>
      <ymax>679</ymax>
    </bndbox>
    <index>0</index>
    <review_code>C_v001</review_code>
  </object>
  <object>
    <name>RoadMark_StopLine</name>
    <pose>Unspecified</pose>
    <truncated>0</truncated>
    <difficult>0</difficult>
    <bndbox>
      <xmin>1156</xmin>
      <ymin>673</ymin>
      <xmax>1282</xmax>
      <ymax>677</ymax>
    </bndbox>
    <index>1</index>
    <review_code>C_v001</review_code>
  </object>
  <object>
    <name>RoadMark_Crosswalk</name>
    <pose>Unspecified</pose>
    <truncated>0</truncated>
    <difficult>0</difficult>
    <bndbox>
      <xmin>1193</xmin>
      <ymin>603</ymin>
      <xmax>1340</xmax>
      <ymax>611</ymax>
    </bndbox>
    <index>2</index>
    <review_code>C_v001</review_code>
  </object>
  <object>
    <name>RoadMark_Crosswalk</name>
    <pose>Unspecified</pose>
    <truncated>0</truncated>
    <difficult>0</difficult>
    <bndbox>
      <xmin>714</xmin>
      <ymin>612</ymin>
      <xmax>763</xmax>
      <ymax>619</ymax>
    </bndbox>
    <index>3</index>
    <review_code>C_v001</review_code>
  </object>
  <object>
    <name>RoadMarkArrow_Straight</name>
    <pose>Unspecified</pose>
    <truncated>0</truncated>
    <difficult>0</difficult>
    <bndbox>
      <xmin>523</xmin>
      <ymin>686</ymin>
      <xmax>618</xmax>
      <ymax>725</ymax>
    </bndbox>
    <index>4</index>
    <review_code>C_v001</review_code>
  </object>
  <object>
    <name>RoadMarkArrow_Straight</name>
    <pose>Unspecified</pose>
    <truncated>0</truncated>
    <difficult>0</difficult>
    <bndbox>
      <xmin>1210</xmin>
      <ymin>683</ymin>
      <xmax>1288</xmax>
      <ymax>715</ymax>
    </bndbox>
    <index>5</index>
    <review_code>C_v001</review_code>
  </object>
  <line>
    <name>Lane_White_Solid</name>
    <pose>Unspecified</pose>
    <truncated>0</truncated>
    <difficult>0</difficult>
    <controlPt>
      <x>762</x>
      <y>703</y>
      <x>680</x>
      <y>792</y>
      <x>474</x>
      <y>980</y>
    </controlPt>
    <index>6</index>
    <review_code>C_v001</review_code>
  </line>
  <line>
    <name>Lane_Blue_Dash</name>
    <pose>Unspecified</pose>
    <truncated>0</truncated>
    <difficult>0</difficult>
    <controlPt>
      <x>1147</x>
      <y>753</y>
      <x>1299</x>
      <y>882</y>
      <x>1423</x>
      <y>990</y>
    </controlPt>
    <index>7</index>
    <review_code>C_v001</review_code>
  </line>
  <line>
    <name>Lane_Blue_Dash</name>
    <pose>Unspecified</pose>
    <truncated>0</truncated>
    <difficult>0</difficult>
    <controlPt>
      <x>1162</x>
      <y>747</y>
      <x>1338</x>
      <y>879</y>
      <x>1475</x>
      <y>987</y>
    </controlPt>
    <index>8</index>
    <review_code>C_v001</review_code>
  </line>
  <line>
    <name>Lane_White_Solid</name>
    <pose>Unspecified</pose>
    <truncated>0</truncated>
    <difficult>0</difficult>
    <controlPt>
      <x>511</x>
      <y>677</y>
      <x>488</x>
      <y>686</y>
    </controlPt>
    <index>9</index>
    <review_code>C_v001</review_code>
  </line>
  <line>
    <name>Lane_Yellow_Solid</name>
    <pose>Unspecified</pose>
    <truncated>0</truncated>
    <difficult>0</difficult>
    <controlPt>
      <x>1760</x>
      <y>754</y>
      <x>1919</x>
      <y>806</y>
    </controlPt>
    <index>10</index>
    <review_code>C_v001</review_code>
  </line>
  <object>
    <name>Vehicle_Car</name>
    <pose>Unspecified</pose>
    <truncated>0</truncated>
    <difficult>0</difficult>
    <bndbox>
      <xmin>0</xmin>
      <ymin>529</ymin>
      <xmax>492</xmax>
      <ymax>936</ymax>
    </bndbox>
    <index>11</index>
    <review_code>C_v001</review_code>
  </object>
  <object>
    <name>Vehicle_Car</name>
    <pose>Unspecified</pose>
    <truncated>0</truncated>
    <difficult>0</difficult>
    <bndbox>
      <xmin>365</xmin>
      <ymin>547</ymin>
      <xmax>507</xmax>
      <ymax>659</ymax>
    </bndbox>
    <index>12</index>
    <review_code>C_v001</review_code>
  </object>
  <object>
    <name>Vehicle_Car</name>
    <pose>Unspecified</pose>
    <truncated>0</truncated>
    <difficult>0</difficult>
    <bndbox>
      <xmin>502</xmin>
      <ymin>573</ymin>
      <xmax>529</xmax>
      <ymax>608</ymax>
    </bndbox>
    <index>13</index>
    <review_code>C_v001</review_code>
  </object>
  <object>
    <name>Vehicle_Car</name>
    <pose>Unspecified</pose>
    <truncated>0</truncated>
    <difficult>0</difficult>
    <bndbox>
      <xmin>509</xmin>
      <ymin>536</ymin>
      <xmax>712</xmax>
      <ymax>696</ymax>
    </bndbox>
    <index>14</index>
    <review_code>C_v001</review_code>
  </object>
  <object>
    <name>Pedestrian_Pedestrian</name>
    <pose>Unspecified</pose>
    <truncated>0</truncated>
    <difficult>0</difficult>
    <bndbox>
      <xmin>715</xmin>
      <ymin>559</ymin>
      <xmax>752</xmax>
      <ymax>631</ymax>
    </bndbox>
    <index>15</index>
    <review_code>C_v001</review_code>
  </object>
  <object>
    <name>Vehicle_Motorcycle</name>
    <pose>Unspecified</pose>
    <truncated>0</truncated>
    <difficult>0</difficult>
    <bndbox>
      <xmin>720</xmin>
      <ymin>583</ymin>
      <xmax>750</xmax>
      <ymax>634</ymax>
    </bndbox>
    <index>16</index>
    <review_code>C_v001</review_code>
  </object>
  <object>
    <name>TrafficLight_Green</name>
    <pose>Unspecified</pose>
    <truncated>0</truncated>
    <difficult>0</difficult>
    <bndbox>
      <xmin>682</xmin>
      <ymin>431</ymin>
      <xmax>725</xmax>
      <ymax>441</ymax>
    </bndbox>
    <index>17</index>
    <review_code>C_v001</review_code>
  </object>
  <object>
    <name>TrafficSign_Else</name>
    <pose>Unspecified</pose>
    <truncated>0</truncated>
    <difficult>0</difficult>
    <bndbox>
      <xmin>724</xmin>
      <ymin>414</ymin>
      <xmax>750</xmax>
      <ymax>439</ymax>
    </bndbox>
    <index>18</index>
    <review_code>C_v001</review_code>
  </object>
  <object>
    <name>Vehicle_Unknown</name>
    <pose>Unspecified</pose>
    <truncated>0</truncated>
    <difficult>0</difficult>
    <bndbox>
      <xmin>762</xmin>
      <ymin>295</ymin>
      <xmax>1156</xmax>
      <ymax>830</ymax>
    </bndbox>
    <index>19</index>
    <review_code>C_v001</review_code>
  </object>
  <object>
    <name>Vehicle_Car</name>
    <pose>Unspecified</pose>
    <truncated>0</truncated>
    <difficult>0</difficult>
    <bndbox>
      <xmin>1155</xmin>
      <ymin>564</ymin>
      <xmax>1191</xmax>
      <ymax>658</ymax>
    </bndbox>
    <index>20</index>
    <review_code>C_v001</review_code>
  </object>
  <object>
    <name>Vehicle_Car</name>
    <pose>Unspecified</pose>
    <truncated>0</truncated>
    <difficult>0</difficult>
    <bndbox>
      <xmin>1175</xmin>
      <ymin>567</ymin>
      <xmax>1227</xmax>
      <ymax>608</ymax>
    </bndbox>
    <index>21</index>
    <review_code>C_v001</review_code>
  </object>
  <object>
    <name>Vehicle_Car</name>
    <pose>Unspecified</pose>
    <truncated>0</truncated>
    <difficult>0</difficult>
    <bndbox>
      <xmin>1226</xmin>
      <ymin>562</ymin>
      <xmax>1300</xmax>
      <ymax>596</ymax>
    </bndbox>
    <index>22</index>
    <review_code>C_v001</review_code>
  </object>
  <object>
    <name>Vehicle_Car</name>
    <pose>Unspecified</pose>
    <truncated>0</truncated>
    <difficult>0</difficult>
    <bndbox>
      <xmin>1296</xmin>
      <ymin>562</ymin>
      <xmax>1364</xmax>
      <ymax>599</ymax>
    </bndbox>
    <index>23</index>
    <review_code>C_v001</review_code>
  </object>
  <object>
    <name>Vehicle_Car</name>
    <pose>Unspecified</pose>
    <truncated>0</truncated>
    <difficult>0</difficult>
    <bndbox>
      <xmin>1358</xmin>
      <ymin>546</ymin>
      <xmax>1401</xmax>
      <ymax>571</ymax>
    </bndbox>
    <index>24</index>
    <review_code>C_v001</review_code>
  </object>
  <object>
    <name>Vehicle_Car</name>
    <pose>Unspecified</pose>
    <truncated>0</truncated>
    <difficult>0</difficult>
    <bndbox>
      <xmin>1285</xmin>
      <ymin>541</ymin>
      <xmax>1757</xmax>
      <ymax>821</ymax>
    </bndbox>
    <index>25</index>
    <review_code>C_v001</review_code>
  </object>
  <object>
    <name>TrafficLight_Red</name>
    <pose>Unspecified</pose>
    <truncated>0</truncated>
    <difficult>0</difficult>
    <bndbox>
      <xmin>1624</xmin>
      <ymin>495</ymin>
      <xmax>1635</xmax>
      <ymax>521</ymax>
    </bndbox>
    <index>26</index>
    <review_code>C_v001</review_code>
  </object>
</annotation>