<?xml version="1.0" encoding="UTF-8"?>
<annotation>
  <ver>v001_1</ver>
  <folder>2</folder>
  <filename>2_20200114_155214_003930.jpg</filename>
  <path>C:\Users\KATECH-01\Desktop\v3\02. 검수_도심로4차_5차_신성례v3\도심로 5차\20200114_155214\2\</path>
  <source>
    <database>KATECH_DB</database>
  </source>
  <size>
    <width>1920</width>
    <height>1080</height>
    <depth>3</depth>
  </size>
  <segmented>0</segmented>
  <index_max>27</index_max>
  <object>
    <name>RoadMark_Character</name>
    <pose>Unspecified</pose>
    <truncated>0</truncated>
    <difficult>0</difficult>
    <bndbox>
      <xmin>432</xmin>
      <ymin>698</ymin>
      <xmax>684</xmax>
      <ymax>725</ymax>
    </bndbox>
    <index>0</index>
    <review_code>C_v001</review_code>
  </object>
  <object>
    <name>RoadMark_Character</name>
    <pose>Unspecified</pose>
    <truncated>0</truncated>
    <difficult>0</difficult>
    <bndbox>
      <xmin>406</xmin>
      <ymin>730</ymin>
      <xmax>616</xmax>
      <ymax>779</ymax>
    </bndbox>
    <index>1</index>
    <review_code>C_v001</review_code>
  </object>
  <object>
    <name>RoadMark_Character</name>
    <pose>Unspecified</pose>
    <truncated>0</truncated>
    <difficult>0</difficult>
    <bndbox>
      <xmin>1275</xmin>
      <ymin>708</ymin>
      <xmax>1521</xmax>
      <ymax>733</ymax>
    </bndbox>
    <index>2</index>
    <review_code>C_v001</review_code>
  </object>
  <object>
    <name>RoadMark_Character</name>
    <pose>Unspecified</pose>
    <truncated>0</truncated>
    <difficult>0</difficult>
    <bndbox>
      <xmin>1330</xmin>
      <ymin>744</ymin>
      <xmax>1694</xmax>
      <ymax>785</ymax>
    </bndbox>
    <index>3</index>
    <review_code>C_v001</review_code>
  </object>
  <object>
    <name>RoadMark_Character</name>
    <pose>Unspecified</pose>
    <truncated>0</truncated>
    <difficult>0</difficult>
    <bndbox>
      <xmin>1769</xmin>
      <ymin>736</ymin>
      <xmax>1918</xmax>
      <ymax>772</ymax>
    </bndbox>
    <index>4</index>
    <review_code>C_v001</review_code>
  </object>
  <line>
    <name>Lane_Yellow_Solid</name>
    <pose>Unspecified</pose>
    <truncated>0</truncated>
    <difficult>0</difficult>
    <controlPt>
      <x>459</x>
      <y>684</y>
      <x>406</x>
      <y>698</y>
    </controlPt>
    <index>5</index>
    <review_code>C_v001</review_code>
  </line>
  <line>
    <name>Lane_White_Dash</name>
    <pose>Unspecified</pose>
    <truncated>0</truncated>
    <difficult>0</difficult>
    <controlPt>
      <x>821</x>
      <y>672</y>
      <x>766</x>
      <y>726</y>
      <x>466</x>
      <y>976</y>
    </controlPt>
    <index>6</index>
    <review_code>C_v001</review_code>
  </line>
  <line>
    <name>Lane_White_Dash</name>
    <pose>Unspecified</pose>
    <truncated>0</truncated>
    <difficult>0</difficult>
    <controlPt>
      <x>1152</x>
      <y>706</y>
      <x>1316</x>
      <y>817</y>
    </controlPt>
    <index>7</index>
    <review_code>C_v001</review_code>
  </line>
  <line>
    <name>Lane_White_Dash</name>
    <pose>Unspecified</pose>
    <truncated>0</truncated>
    <difficult>0</difficult>
    <controlPt>
      <x>1395</x>
      <y>680</y>
      <x>1667</x>
      <y>744</y>
    </controlPt>
    <index>8</index>
    <review_code>C_v001</review_code>
  </line>
  <object>
    <name>TrafficSign_Else</name>
    <pose>Unspecified</pose>
    <truncated>0</truncated>
    <difficult>0</difficult>
    <bndbox>
      <xmin>1685</xmin>
      <ymin>468</ymin>
      <xmax>1734</xmax>
      <ymax>510</ymax>
    </bndbox>
    <index>9</index>
    <review_code>C_v001</review_code>
  </object>
  <object>
    <name>TrafficSign_Else</name>
    <pose>Unspecified</pose>
    <truncated>0</truncated>
    <difficult>0</difficult>
    <bndbox>
      <xmin>1430</xmin>
      <ymin>485</ymin>
      <xmax>1453</xmax>
      <ymax>513</ymax>
    </bndbox>
    <index>10</index>
    <review_code>C_v001</review_code>
  </object>
  <object>
    <name>TrafficLight_Red</name>
    <pose>Unspecified</pose>
    <truncated>0</truncated>
    <difficult>0</difficult>
    <bndbox>
      <xmin>837</xmin>
      <ymin>452</ymin>
      <xmax>865</xmax>
      <ymax>462</ymax>
    </bndbox>
    <index>11</index>
    <review_code>C_v001</review_code>
  </object>
  <object>
    <name>TrafficLight_Red</name>
    <pose>Unspecified</pose>
    <truncated>0</truncated>
    <difficult>0</difficult>
    <bndbox>
      <xmin>915</xmin>
      <ymin>452</ymin>
      <xmax>943</xmax>
      <ymax>463</ymax>
    </bndbox>
    <index>12</index>
    <review_code>C_v001</review_code>
  </object>
  <object>
    <name>TrafficLight_Red</name>
    <pose>Unspecified</pose>
    <truncated>0</truncated>
    <difficult>0</difficult>
    <bndbox>
      <xmin>992</xmin>
      <ymin>454</ymin>
      <xmax>1019</xmax>
      <ymax>465</ymax>
    </bndbox>
    <index>13</index>
    <review_code>C_v001</review_code>
  </object>
  <object>
    <name>TrafficLight_Red</name>
    <pose>Unspecified</pose>
    <truncated>0</truncated>
    <difficult>0</difficult>
    <bndbox>
      <xmin>844</xmin>
      <ymin>490</ymin>
      <xmax>865</xmax>
      <ymax>499</ymax>
    </bndbox>
    <index>14</index>
    <review_code>C_v001</review_code>
  </object>
  <object>
    <name>Vehicle_Car</name>
    <pose>Unspecified</pose>
    <truncated>0</truncated>
    <difficult>0</difficult>
    <bndbox>
      <xmin>0</xmin>
      <ymin>505</ymin>
      <xmax>406</xmax>
      <ymax>934</ymax>
    </bndbox>
    <index>15</index>
    <review_code>C_v001</review_code>
  </object>
  <object>
    <name>Vehicle_Car</name>
    <pose>Unspecified</pose>
    <truncated>0</truncated>
    <difficult>0</difficult>
    <bndbox>
      <xmin>452</xmin>
      <ymin>535</ymin>
      <xmax>722</xmax>
      <ymax>704</ymax>
    </bndbox>
    <index>16</index>
    <review_code>C_v001</review_code>
  </object>
  <object>
    <name>Vehicle_Car</name>
    <pose>Unspecified</pose>
    <truncated>0</truncated>
    <difficult>0</difficult>
    <bndbox>
      <xmin>683</xmin>
      <ymin>551</ymin>
      <xmax>798</xmax>
      <ymax>652</ymax>
    </bndbox>
    <index>17</index>
    <review_code>C_v001</review_code>
  </object>
  <object>
    <name>Vehicle_Car</name>
    <pose>Unspecified</pose>
    <truncated>0</truncated>
    <difficult>0</difficult>
    <bndbox>
      <xmin>736</xmin>
      <ymin>544</ymin>
      <xmax>822</xmax>
      <ymax>631</ymax>
    </bndbox>
    <index>18</index>
    <review_code>C_v001</review_code>
  </object>
  <object>
    <name>Vehicle_Car</name>
    <pose>Unspecified</pose>
    <truncated>0</truncated>
    <difficult>0</difficult>
    <bndbox>
      <xmin>802</xmin>
      <ymin>554</ymin>
      <xmax>829</xmax>
      <ymax>621</ymax>
    </bndbox>
    <index>19</index>
    <review_code>C_v001</review_code>
  </object>
  <object>
    <name>Vehicle_Car</name>
    <pose>Unspecified</pose>
    <truncated>0</truncated>
    <difficult>0</difficult>
    <bndbox>
      <xmin>815</xmin>
      <ymin>559</ymin>
      <xmax>835</xmax>
      <ymax>616</ymax>
    </bndbox>
    <index>20</index>
    <review_code>C_v001</review_code>
  </object>
  <object>
    <name>Vehicle_Bus</name>
    <pose>Unspecified</pose>
    <truncated>0</truncated>
    <difficult>0</difficult>
    <bndbox>
      <xmin>875</xmin>
      <ymin>471</ymin>
      <xmax>1006</xmax>
      <ymax>559</ymax>
    </bndbox>
    <index>21</index>
    <review_code>C_v001</review_code>
  </object>
  <object>
    <name>Vehicle_Car</name>
    <pose>Unspecified</pose>
    <truncated>0</truncated>
    <difficult>0</difficult>
    <bndbox>
      <xmin>820</xmin>
      <ymin>537</ymin>
      <xmax>1151</xmax>
      <ymax>796</ymax>
    </bndbox>
    <index>22</index>
    <review_code>C_v001</review_code>
  </object>
  <object>
    <name>Vehicle_Car</name>
    <pose>Unspecified</pose>
    <truncated>0</truncated>
    <difficult>0</difficult>
    <bndbox>
      <xmin>1103</xmin>
      <ymin>547</ymin>
      <xmax>1213</xmax>
      <ymax>639</ymax>
    </bndbox>
    <index>23</index>
    <review_code>C_v001</review_code>
  </object>
  <object>
    <name>Vehicle_Car</name>
    <pose>Unspecified</pose>
    <truncated>0</truncated>
    <difficult>0</difficult>
    <bndbox>
      <xmin>1164</xmin>
      <ymin>552</ymin>
      <xmax>1403</xmax>
      <ymax>703</ymax>
    </bndbox>
    <index>24</index>
    <review_code>C_v001</review_code>
  </object>
  <object>
    <name>Vehicle_Car</name>
    <pose>Unspecified</pose>
    <truncated>0</truncated>
    <difficult>0</difficult>
    <bndbox>
      <xmin>1382</xmin>
      <ymin>577</ymin>
      <xmax>1414</xmax>
      <ymax>602</ymax>
    </bndbox>
    <index>25</index>
    <review_code>C_v001</review_code>
  </object>
  <object>
    <name>Vehicle_Car</name>
    <pose>Unspecified</pose>
    <truncated>0</truncated>
    <difficult>0</difficult>
    <bndbox>
      <xmin>1395</xmin>
      <ymin>540</ymin>
      <xmax>1621</xmax>
      <ymax>687</ymax>
    </bndbox>
    <index>26</index>
    <review_code>C_v001</review_code>
  </object>
  <object>
    <name>Vehicle_Car</name>
    <pose>Unspecified</pose>
    <truncated>0</truncated>
    <difficult>0</difficult>
    <bndbox>
      <xmin>1620</xmin>
      <ymin>527</ymin>
      <xmax>1919</xmax>
      <ymax>742</ymax>
    </bndbox>
    <index>27</index>
    <review_code>C_v001</review_code>
  </object>
</annotation>