<?xml version="1.0" encoding="UTF-8"?>
<annotation>
  <ver>v001_1</ver>
  <folder>2</folder>
  <filename>2_20191018_150814_000750.jpg</filename>
  <path>C:\10. 검수데이타\도심로 2차\20191018_150814(우회전)_186f\2\</path>
  <source>
    <database>KATECH_DB</database>
  </source>
  <size>
    <width>1920</width>
    <height>1080</height>
    <depth>3</depth>
  </size>
  <segmented>0</segmented>
  <index_max>52</index_max>
  <object>
    <name>RoadMark_Crosswalk</name>
    <pose>Unspecified</pose>
    <truncated>0</truncated>
    <difficult>0</difficult>
    <bndbox>
      <xmin>0</xmin>
      <ymin>608</ymin>
      <xmax>718</xmax>
      <ymax>680</ymax>
    </bndbox>
    <index>2</index>
    <review_code>C_v001</review_code>
  </object>
  <object>
    <name>RoadMark_Crosswalk</name>
    <pose>Unspecified</pose>
    <truncated>0</truncated>
    <difficult>0</difficult>
    <bndbox>
      <xmin>856</xmin>
      <ymin>661</ymin>
      <xmax>1682</xmax>
      <ymax>800</ymax>
    </bndbox>
    <index>3</index>
    <review_code>C_v001</review_code>
  </object>
  <object>
    <name>RoadMark_StopLine</name>
    <pose>Unspecified</pose>
    <truncated>0</truncated>
    <difficult>0</difficult>
    <bndbox>
      <xmin>654</xmin>
      <ymin>775</ymin>
      <xmax>1678</xmax>
      <ymax>865</ymax>
    </bndbox>
    <index>4</index>
    <review_code>C_v001</review_code>
  </object>
  <object>
    <name>RoadMark_StopLine</name>
    <pose>Unspecified</pose>
    <truncated>0</truncated>
    <difficult>0</difficult>
    <bndbox>
      <xmin>1549</xmin>
      <ymin>880</ymin>
      <xmax>1871</xmax>
      <ymax>961</ymax>
    </bndbox>
    <index>5</index>
    <review_code>C_v001</review_code>
  </object>
  <line>
    <name>Lane_White_Solid</name>
    <pose>Unspecified</pose>
    <truncated>0</truncated>
    <difficult>0</difficult>
    <controlPt>
      <x>689</x>
      <y>865</y>
      <x>545</x>
      <y>990</y>
    </controlPt>
    <index>6</index>
    <review_code>C_v001</review_code>
  </line>
  <line>
    <name>Lane_Yellow_Solid</name>
    <pose>Unspecified</pose>
    <truncated>0</truncated>
    <difficult>0</difficult>
    <controlPt>
      <x>1776</x>
      <y>616</y>
      <x>1752</x>
      <y>625</y>
      <x>1725</x>
      <y>641</y>
      <x>1711</x>
      <y>657</y>
    </controlPt>
    <index>7</index>
    <review_code>C_v001</review_code>
  </line>
  <line>
    <name>Lane_White_Dash</name>
    <pose>Unspecified</pose>
    <truncated>0</truncated>
    <difficult>0</difficult>
    <controlPt>
      <x>1640</x>
      <y>611</y>
      <x>1522</x>
      <y>636</y>
    </controlPt>
    <index>8</index>
    <review_code>C_v001</review_code>
  </line>
  <object>
    <name>RoadMark_Character</name>
    <pose>Unspecified</pose>
    <truncated>0</truncated>
    <difficult>0</difficult>
    <bndbox>
      <xmin>1470</xmin>
      <ymin>622</ymin>
      <xmax>1566</xmax>
      <ymax>632</ymax>
    </bndbox>
    <index>9</index>
    <review_code>C_v001</review_code>
  </object>
  <object>
    <name>RoadMark_Character</name>
    <pose>Unspecified</pose>
    <truncated>0</truncated>
    <difficult>0</difficult>
    <bndbox>
      <xmin>1569</xmin>
      <ymin>624</ymin>
      <xmax>1729</xmax>
      <ymax>633</ymax>
    </bndbox>
    <index>10</index>
    <review_code>C_v001</review_code>
  </object>
  <object>
    <name>RoadMarkArrow_Straight</name>
    <pose>Unspecified</pose>
    <truncated>0</truncated>
    <difficult>0</difficult>
    <bndbox>
      <xmin>1513</xmin>
      <ymin>612</ymin>
      <xmax>1568</xmax>
      <ymax>621</ymax>
    </bndbox>
    <index>11</index>
    <review_code>C_v001</review_code>
  </object>
  <object>
    <name>RoadMarkArrow_Straight</name>
    <pose>Unspecified</pose>
    <truncated>0</truncated>
    <difficult>0</difficult>
    <bndbox>
      <xmin>1667</xmin>
      <ymin>612</ymin>
      <xmax>1710</xmax>
      <ymax>622</ymax>
    </bndbox>
    <index>12</index>
    <review_code>C_v001</review_code>
  </object>
  <object>
    <name>RoadMark_StopLine</name>
    <pose>Unspecified</pose>
    <truncated>0</truncated>
    <difficult>0</difficult>
    <bndbox>
      <xmin>1514</xmin>
      <ymin>605</ymin>
      <xmax>1662</xmax>
      <ymax>609</ymax>
    </bndbox>
    <index>13</index>
    <review_code>C_v001</review_code>
  </object>
  <object>
    <name>TrafficSign_Else</name>
    <pose>Unspecified</pose>
    <truncated>0</truncated>
    <difficult>0</difficult>
    <bndbox>
      <xmin>370</xmin>
      <ymin>511</ymin>
      <xmax>392</xmax>
      <ymax>532</ymax>
    </bndbox>
    <index>14</index>
    <review_code>C_v001</review_code>
  </object>
  <object>
    <name>Pedestrian_Bicycle</name>
    <pose>Unspecified</pose>
    <truncated>0</truncated>
    <difficult>0</difficult>
    <bndbox>
      <xmin>656</xmin>
      <ymin>591</ymin>
      <xmax>808</xmax>
      <ymax>700</ymax>
    </bndbox>
    <index>15</index>
    <review_code>C_v001</review_code>
  </object>
  <object>
    <name>Pedestrian_Pedestrian</name>
    <pose>Unspecified</pose>
    <truncated>0</truncated>
    <difficult>0</difficult>
    <bndbox>
      <xmin>743</xmin>
      <ymin>510</ymin>
      <xmax>797</xmax>
      <ymax>587</ymax>
    </bndbox>
    <index>16</index>
    <review_code>C_v001</review_code>
  </object>
  <object>
    <name>Pedestrian_Pedestrian</name>
    <pose>Unspecified</pose>
    <truncated>0</truncated>
    <difficult>0</difficult>
    <bndbox>
      <xmin>705</xmin>
      <ymin>515</ymin>
      <xmax>813</xmax>
      <ymax>692</ymax>
    </bndbox>
    <index>17</index>
    <review_code>C_v001</review_code>
  </object>
  <object>
    <name>Pedestrian_Pedestrian</name>
    <pose>Unspecified</pose>
    <truncated>0</truncated>
    <difficult>0</difficult>
    <bndbox>
      <xmin>549</xmin>
      <ymin>557</ymin>
      <xmax>586</xmax>
      <ymax>660</ymax>
    </bndbox>
    <index>18</index>
    <review_code>C_v001</review_code>
  </object>
  <object>
    <name>Pedestrian_Pedestrian</name>
    <pose>Unspecified</pose>
    <truncated>0</truncated>
    <difficult>0</difficult>
    <bndbox>
      <xmin>179</xmin>
      <ymin>564</ymin>
      <xmax>193</xmax>
      <ymax>606</ymax>
    </bndbox>
    <index>19</index>
    <review_code>C_v001</review_code>
  </object>
  <object>
    <name>Pedestrian_Pedestrian</name>
    <pose>Unspecified</pose>
    <truncated>0</truncated>
    <difficult>0</difficult>
    <bndbox>
      <xmin>265</xmin>
      <ymin>554</ymin>
      <xmax>291</xmax>
      <ymax>657</ymax>
    </bndbox>
    <index>20</index>
    <review_code>C_v001</review_code>
  </object>
  <object>
    <name>Pedestrian_Pedestrian</name>
    <pose>Unspecified</pose>
    <truncated>0</truncated>
    <difficult>0</difficult>
    <bndbox>
      <xmin>241</xmin>
      <ymin>544</ymin>
      <xmax>288</xmax>
      <ymax>674</ymax>
    </bndbox>
    <index>21</index>
    <review_code>C_v001</review_code>
  </object>
  <object>
    <name>Pedestrian_Pedestrian</name>
    <pose>Unspecified</pose>
    <truncated>0</truncated>
    <difficult>0</difficult>
    <bndbox>
      <xmin>459</xmin>
      <ymin>557</ymin>
      <xmax>475</xmax>
      <ymax>620</ymax>
    </bndbox>
    <index>22</index>
    <review_code>C_v001</review_code>
  </object>
  <object>
    <name>Pedestrian_Pedestrian</name>
    <pose>Unspecified</pose>
    <truncated>0</truncated>
    <difficult>0</difficult>
    <bndbox>
      <xmin>1403</xmin>
      <ymin>525</ymin>
      <xmax>1431</xmax>
      <ymax>575</ymax>
    </bndbox>
    <index>23</index>
    <review_code>C_v001</review_code>
  </object>
  <object>
    <name>Pedestrian_Pedestrian</name>
    <pose>Unspecified</pose>
    <truncated>0</truncated>
    <difficult>0</difficult>
    <bndbox>
      <xmin>1430</xmin>
      <ymin>541</ymin>
      <xmax>1439</xmax>
      <ymax>578</ymax>
    </bndbox>
    <index>24</index>
    <review_code>C_v001</review_code>
  </object>
  <object>
    <name>Pedestrian_Pedestrian</name>
    <pose>Unspecified</pose>
    <truncated>0</truncated>
    <difficult>0</difficult>
    <bndbox>
      <xmin>1516</xmin>
      <ymin>543</ymin>
      <xmax>1523</xmax>
      <ymax>572</ymax>
    </bndbox>
    <index>25</index>
    <review_code>C_v001</review_code>
  </object>
  <object>
    <name>Pedestrian_Pedestrian</name>
    <pose>Unspecified</pose>
    <truncated>0</truncated>
    <difficult>0</difficult>
    <bndbox>
      <xmin>1459</xmin>
      <ymin>539</ymin>
      <xmax>1470</xmax>
      <ymax>577</ymax>
    </bndbox>
    <index>26</index>
    <review_code>C_v001</review_code>
  </object>
  <object>
    <name>Pedestrian_Pedestrian</name>
    <pose>Unspecified</pose>
    <truncated>0</truncated>
    <difficult>0</difficult>
    <bndbox>
      <xmin>1478</xmin>
      <ymin>548</ymin>
      <xmax>1488</xmax>
      <ymax>574</ymax>
    </bndbox>
    <index>27</index>
    <review_code>C_v001</review_code>
  </object>
  <object>
    <name>Pedestrian_Pedestrian</name>
    <pose>Unspecified</pose>
    <truncated>0</truncated>
    <difficult>0</difficult>
    <bndbox>
      <xmin>1470</xmin>
      <ymin>548</ymin>
      <xmax>1477</xmax>
      <ymax>573</ymax>
    </bndbox>
    <index>28</index>
    <review_code>C_v001</review_code>
  </object>
  <object>
    <name>Pedestrian_Pedestrian</name>
    <pose>Unspecified</pose>
    <truncated>0</truncated>
    <difficult>0</difficult>
    <bndbox>
      <xmin>1447</xmin>
      <ymin>543</ymin>
      <xmax>1457</xmax>
      <ymax>577</ymax>
    </bndbox>
    <index>29</index>
    <review_code>C_v001</review_code>
  </object>
  <object>
    <name>Vehicle_Car</name>
    <pose>Unspecified</pose>
    <truncated>0</truncated>
    <difficult>0</difficult>
    <bndbox>
      <xmin>1778</xmin>
      <ymin>544</ymin>
      <xmax>1809</xmax>
      <ymax>561</ymax>
    </bndbox>
    <index>30</index>
    <review_code>C_v001</review_code>
  </object>
  <object>
    <name>Vehicle_Car</name>
    <pose>Unspecified</pose>
    <truncated>0</truncated>
    <difficult>0</difficult>
    <bndbox>
      <xmin>1748</xmin>
      <ymin>542</ymin>
      <xmax>1773</xmax>
      <ymax>560</ymax>
    </bndbox>
    <index>31</index>
    <review_code>C_v001</review_code>
  </object>
  <object>
    <name>Vehicle_Unknown</name>
    <pose>Unspecified</pose>
    <truncated>0</truncated>
    <difficult>0</difficult>
    <bndbox>
      <xmin>1724</xmin>
      <ymin>538</ymin>
      <xmax>1757</xmax>
      <ymax>565</ymax>
    </bndbox>
    <index>32</index>
    <review_code>C_v001</review_code>
  </object>
  <object>
    <name>Vehicle_Unknown</name>
    <pose>Unspecified</pose>
    <truncated>0</truncated>
    <difficult>0</difficult>
    <bndbox>
      <xmin>1591</xmin>
      <ymin>539</ymin>
      <xmax>1652</xmax>
      <ymax>571</ymax>
    </bndbox>
    <index>33</index>
    <review_code>C_v001</review_code>
  </object>
  <object>
    <name>Vehicle_Unknown</name>
    <pose>Unspecified</pose>
    <truncated>0</truncated>
    <difficult>0</difficult>
    <bndbox>
      <xmin>1587</xmin>
      <ymin>520</ymin>
      <xmax>1654</xmax>
      <ymax>551</ymax>
    </bndbox>
    <index>34</index>
    <review_code>C_v001</review_code>
  </object>
  <object>
    <name>Vehicle_Unknown</name>
    <pose>Unspecified</pose>
    <truncated>0</truncated>
    <difficult>0</difficult>
    <bndbox>
      <xmin>1527</xmin>
      <ymin>528</ymin>
      <xmax>1589</xmax>
      <ymax>572</ymax>
    </bndbox>
    <index>35</index>
    <review_code>C_v001</review_code>
  </object>
  <object>
    <name>Vehicle_Car</name>
    <pose>Unspecified</pose>
    <truncated>0</truncated>
    <difficult>0</difficult>
    <bndbox>
      <xmin>1537</xmin>
      <ymin>545</ymin>
      <xmax>1589</xmax>
      <ymax>573</ymax>
    </bndbox>
    <index>36</index>
    <review_code>C_v001</review_code>
  </object>
  <object>
    <name>Vehicle_Bus</name>
    <pose>Unspecified</pose>
    <truncated>0</truncated>
    <difficult>0</difficult>
    <bndbox>
      <xmin>1514</xmin>
      <ymin>521</ymin>
      <xmax>1574</xmax>
      <ymax>529</ymax>
    </bndbox>
    <index>37</index>
    <review_code>C_v001</review_code>
  </object>
  <object>
    <name>Vehicle_Unknown</name>
    <pose>Unspecified</pose>
    <truncated>0</truncated>
    <difficult>0</difficult>
    <bndbox>
      <xmin>1347</xmin>
      <ymin>506</ymin>
      <xmax>1457</xmax>
      <ymax>540</ymax>
    </bndbox>
    <index>38</index>
    <review_code>C_v001</review_code>
  </object>
  <object>
    <name>Vehicle_Bus</name>
    <pose>Unspecified</pose>
    <truncated>0</truncated>
    <difficult>0</difficult>
    <bndbox>
      <xmin>1066</xmin>
      <ymin>497</ymin>
      <xmax>1347</xmax>
      <ymax>535</ymax>
    </bndbox>
    <index>39</index>
    <review_code>C_v001</review_code>
  </object>
  <object>
    <name>Vehicle_Bus</name>
    <pose>Unspecified</pose>
    <truncated>0</truncated>
    <difficult>0</difficult>
    <bndbox>
      <xmin>716</xmin>
      <ymin>494</ymin>
      <xmax>1057</xmax>
      <ymax>607</ymax>
    </bndbox>
    <index>40</index>
    <review_code>C_v001</review_code>
  </object>
  <object>
    <name>Vehicle_Car</name>
    <pose>Unspecified</pose>
    <truncated>0</truncated>
    <difficult>0</difficult>
    <bndbox>
      <xmin>701</xmin>
      <ymin>563</ymin>
      <xmax>730</xmax>
      <ymax>599</ymax>
    </bndbox>
    <index>41</index>
    <review_code>C_v001</review_code>
  </object>
  <object>
    <name>Vehicle_Car</name>
    <pose>Unspecified</pose>
    <truncated>0</truncated>
    <difficult>0</difficult>
    <bndbox>
      <xmin>688</xmin>
      <ymin>552</ymin>
      <xmax>732</xmax>
      <ymax>563</ymax>
    </bndbox>
    <index>42</index>
    <review_code>C_v001</review_code>
  </object>
  <object>
    <name>Vehicle_Car</name>
    <pose>Unspecified</pose>
    <truncated>0</truncated>
    <difficult>0</difficult>
    <bndbox>
      <xmin>579</xmin>
      <ymin>555</ymin>
      <xmax>701</xmax>
      <ymax>601</ymax>
    </bndbox>
    <index>43</index>
    <review_code>C_v001</review_code>
  </object>
  <object>
    <name>Vehicle_Unknown</name>
    <pose>Unspecified</pose>
    <truncated>0</truncated>
    <difficult>0</difficult>
    <bndbox>
      <xmin>533</xmin>
      <ymin>545</ymin>
      <xmax>681</xmax>
      <ymax>606</ymax>
    </bndbox>
    <index>44</index>
    <review_code>C_v001</review_code>
  </object>
  <object>
    <name>Vehicle_Car</name>
    <pose>Unspecified</pose>
    <truncated>0</truncated>
    <difficult>0</difficult>
    <bndbox>
      <xmin>492</xmin>
      <ymin>573</ymin>
      <xmax>532</xmax>
      <ymax>604</ymax>
    </bndbox>
    <index>45</index>
    <review_code>C_v001</review_code>
  </object>
  <object>
    <name>Vehicle_Car</name>
    <pose>Unspecified</pose>
    <truncated>0</truncated>
    <difficult>0</difficult>
    <bndbox>
      <xmin>344</xmin>
      <ymin>570</ymin>
      <xmax>461</xmax>
      <ymax>612</ymax>
    </bndbox>
    <index>46</index>
    <review_code>C_v001</review_code>
  </object>
  <object>
    <name>Vehicle_Car</name>
    <pose>Unspecified</pose>
    <truncated>0</truncated>
    <difficult>0</difficult>
    <bndbox>
      <xmin>163</xmin>
      <ymin>576</ymin>
      <xmax>241</xmax>
      <ymax>605</ymax>
    </bndbox>
    <index>47</index>
    <review_code>C_v001</review_code>
  </object>
  <object>
    <name>Vehicle_Bus</name>
    <pose>Unspecified</pose>
    <truncated>0</truncated>
    <difficult>0</difficult>
    <bndbox>
      <xmin>34</xmin>
      <ymin>551</ymin>
      <xmax>162</xmax>
      <ymax>606</ymax>
    </bndbox>
    <index>48</index>
    <review_code>C_v001</review_code>
  </object>
  <object>
    <name>Vehicle_Car</name>
    <pose>Unspecified</pose>
    <truncated>0</truncated>
    <difficult>0</difficult>
    <bndbox>
      <xmin>4</xmin>
      <ymin>581</ymin>
      <xmax>34</xmax>
      <ymax>607</ymax>
    </bndbox>
    <index>49</index>
    <review_code>C_v001</review_code>
  </object>
  <object>
    <name>Vehicle_Car</name>
    <pose>Unspecified</pose>
    <truncated>0</truncated>
    <difficult>0</difficult>
    <bndbox>
      <xmin>1669</xmin>
      <ymin>545</ymin>
      <xmax>1919</xmax>
      <ymax>913</ymax>
    </bndbox>
    <index>50</index>
    <review_code>C_v001</review_code>
  </object>
  <object>
    <name>Vehicle_Car</name>
    <pose>Unspecified</pose>
    <truncated>0</truncated>
    <difficult>0</difficult>
    <bndbox>
      <xmin>936</xmin>
      <ymin>529</ymin>
      <xmax>1561</xmax>
      <ymax>989</ymax>
    </bndbox>
    <index>51</index>
    <review_code>C_v001</review_code>
  </object>
  <line>
    <name>Lane_White_Solid</name>
    <pose>Unspecified</pose>
    <truncated>0</truncated>
    <difficult>0</difficult>
    <controlPt>
      <x>1505</x>
      <y>610</y>
      <x>1467</x>
      <y>617</y>
    </controlPt>
    <index>52</index>
    <review_code>C_v001</review_code>
  </line>
</annotation>